{"id": "abafd6b755925ba148582d48", "source": "MAG 196 - This Old House Transcript-converted.pdf", "title": "MAG 196 - This Old House Transcript-converted", "text": "As long as he listens to me first, it won’t matter. \n[Tape click] \n\nThe Magnus Archives – MAG 196 – This Old House \n \n22 \nARCHIVIST ON TAPE \n(From left side) So just listen— \n[Tape click] \nARCHIVIST ON TAPE \n(From right side) (Crosstalk) Listen Martin, you should know— \n[Tape click] \nARCHIVIST ON TAPE \n(From middle-left side) (Crosstalk) Now, listen to me, Martin, li-listen— \n[Tape click] \nMARTIN \nWait. Wait… \nThe tapes... \nANNABELLE \nA fine material to spin a web with, don’t you think? \nMARTIN \nWhat? All this time, through all of this, it, it was just you spying on us? \nANNABELLE \nOh Martin. You have no idea who’s listening, do you? \n[Tape clicks off] \n[The Magnus Archives Theme – Outro] \n\nThe Magnus Archives – MAG 196 – This Old House \n \n23 \nJONATHAN SIMS \nThe Magnus Archives is a podcast distributed by Rusty Quill and licensed under \na Creative Commons Attribution Non-Commercial ShareAlike 4.0 International \nlicence. Today’s episode was written by Jonathan Sims, produced by Lowri Ann \nDavies, and directed by Alexander J Newall. It featured: Alexander J Newall as \nMartin Blackwood and Chioma Nwalioba as Annabelle Cane. To subscribe, buy \nmerchandise, or join our Patreon, visit rustyquill.com. Rate and review us \nonline, tweet us at TheRustyQuill, visit us on Facebook, or email us via \nmail@rustyquill.com. Join our community on the Discord via the website, or on \nReddit, at r/TheMagnusArchives. Thanks for listening.", "metadata": {"chunk_index": 6, "chunk_count": 7, "chars": 1440}}