{"id": "c6fa072308c2e9d465605b54", "source": "MAG 148 - Extended Surveillance Transcript.pdf", "title": "MAG 148 - Extended Surveillance Transcript", "text": "g too many questions for \nthe folks upstairs, I think. I wanted to know why Samson hadn’t signed out of \nthe building before he disappeared, why no matter who tried to reset the \nsystem, it always logged back in as him. Or why, whenever I was watching the \nmonitors alone, I’d see him on that old CRT screen, staring right back at me, \nquietly calling for me to join him. \nARCHIVIST \nStatement ends. \nHmm. Better. Does reading a statement of the Ceaseless Watcher count as a \nsort of auto-cannibalism, I wonder? Or some sort of bird-like regurgitation of \nfear, re-consuming second-hand terror? Whatever the analogy, I’m finding it \nharder and harder to ignore the diminishing returns, how much less \n\nThe Magnus Archives – 148 – Extended Surveillance \n \n19 \n \nsatisfaction each one gives me. My desire for follow-up, for verification, for \nproper digestion of the experience, it grows less and less. I honestly don’t care \nif Mr Maraj was chased down and consumed by his voyeuristic former friend, \nor if he has forgotten the whole affair, living in blissful ignorance. I just find my \nmind already wandering to the next statement, and the hopes that it won’t be \nquite as stale. \nEnd recording. \n[Tape clicks off.] \n[The Magnus Archives Theme – Outro] \nThe Magnus Archives is a podcast distributed by Rusty Quill and licensed under \na Creative Commons Attribution Non-Commercial Sharealike 4.0 International \nlicence. \nToday’s episode was written by Jonathan Sims and directed by Alexander J \nNewall. \nIt featured: Jonathan Sims as the Archivist, Frank Voss as Basira Hussain, and \nBen Meredith as Elias Bouchard.", "metadata": {"chunk_index": 7, "chunk_count": 8, "chars": 1615}}